kov_utils/__init__.py
kov_utils/kjson.py
kov_utils/paths.py
kov_utils/rand.py
kov_utils/request.py
kov_utils/sh.py
kov_utils/strings.py
kov_utils-0.0.2.dist-info/LICENSE
kov_utils-0.0.2.dist-info/METADATA
kov_utils-0.0.2.dist-info/WHEEL
kov_utils-0.0.2.dist-info/top_level.txt
kov_utils-0.0.2.dist-info/RECORD
