Metadata-Version: 2.1
Name: kov-utils
Version: 0.0.2
Summary: A small utils package
Home-page: https://github.com/Zselter07/Utilities
Author: Pentek Zsolt
Author-email: zsoltpentek@yahoo.com
License: UNKNOWN
Platform: UNKNOWN
Classifier: Programming Language :: Python :: 3
Classifier: License :: OSI Approved :: MIT License
Classifier: Operating System :: OS Independent
Requires-Python: >=3.6
Requires-Dist: fake-useragent
